{"frames":{"paths_0011":{"frame":{"x":0,"y":0,"w":312,"h":312},"rotated":false,"trimmed":false,"spriteSourceSize":{"x":0,"y":0,"w":312,"h":312},"sourceSize":{"w":312,"h":312}},"paths_0101":{"frame":{"x":0,"y":313,"w":312,"h":312},"rotated":false,"trimmed":false,"spriteSourceSize":{"x":0,"y":0,"w":312,"h":312},"sourceSize":{"w":312,"h":312}},"paths_0110":{"frame":{"x":313,"y":0,"w":312,"h":312},"rotated":false,"trimmed":false,"spriteSourceSize":{"x":0,"y":0,"w":312,"h":312},"sourceSize":{"w":312,"h":312}},"paths_0111":{"frame":{"x":313,"y":313,"w":312,"h":312},"rotated":false,"trimmed":false,"spriteSourceSize":{"x":0,"y":0,"w":312,"h":312},"sourceSize":{"w":312,"h":312}},"paths_1001":{"frame":{"x":0,"y":626,"w":312,"h":312},"rotated":false,"trimmed":false,"spriteSourceSize":{"x":0,"y":0,"w":312,"h":312},"sourceSize":{"w":312,"h":312}},"paths_1010":{"frame":{"x":313,"y":626,"w":312,"h":312},"rotated":false,"trimmed":false,"spriteSourceSize":{"x":0,"y":0,"w":312,"h":312},"sourceSize":{"w":312,"h":312}},"paths_1011":{"frame":{"x":626,"y":0,"w":312,"h":312},"rotated":false,"trimmed":false,"spriteSourceSize":{"x":0,"y":0,"w":312,"h":312},"sourceSize":{"w":312,"h":312}},"paths_1100":{"frame":{"x":626,"y":313,"w":312,"h":312},"rotated":false,"trimmed":false,"spriteSourceSize":{"x":0,"y":0,"w":312,"h":312},"sourceSize":{"w":312,"h":312}},"paths_1101":{"frame":{"x":626,"y":626,"w":312,"h":312},"rotated":false,"trimmed":false,"spriteSourceSize":{"x":0,"y":0,"w":312,"h":312},"sourceSize":{"w":312,"h":312}},"paths_1110":{"frame":{"x":0,"y":939,"w":312,"h":312},"rotated":false,"trimmed":false,"spriteSourceSize":{"x":0,"y":0,"w":312,"h":312},"sourceSize":{"w":312,"h":312}},"paths_1111":{"frame":{"x":313,"y":939,"w":312,"h":312},"rotated":false,"trimmed":false,"spriteSourceSize":{"x":0,"y":0,"w":312,"h":312},"sourceSize":{"w":312,"h":312}}},"meta":{"app":"https://www.leshylabs.com/apps/sstool/","version":"Leshy SpriteSheet Tool v0.8.4","image":"tile_paths.png","size":{"w":938,"h":1251},"scale":1}}